django_multi_manifest_loader/__init__.py
django_multi_manifest_loader/templatetags/__init__.py
django_multi_manifest_loader/templatetags/manifest.py
django_multi_manifest_loader-0.1.3.dist-info/licenses/LICENSE
django_multi_manifest_loader-0.1.3.dist-info/METADATA
django_multi_manifest_loader-0.1.3.dist-info/WHEEL
django_multi_manifest_loader-0.1.3.dist-info/top_level.txt
django_multi_manifest_loader-0.1.3.dist-info/RECORD
