Metadata-Version: 2.4
Name: django-multi-manifest-loader
Version: 0.1.3
Summary: Standalone template tag for loading webpack manifest files from multiple Django packages/apps
Author-email: Pescheck <devops@pescheck.nl>
License-Expression: MIT
Project-URL: Homepage, https://github.com/pescheckit/django-multi-manifest-loader
Project-URL: Bug Reports, https://github.com/pescheckit/django-multi-manifest-loader/issues
Project-URL: Source, https://github.com/pescheckit/django-multi-manifest-loader
Keywords: django,webpack,manifest,cache-busting,static-files
Classifier: Development Status :: 4 - Beta
Classifier: Environment :: Web Environment
Classifier: Framework :: Django
Classifier: Framework :: Django :: 4.0
Classifier: Framework :: Django :: 4.1
Classifier: Framework :: Django :: 4.2
Classifier: Framework :: Django :: 5.0
Classifier: Framework :: Django :: 5.1
Classifier: Intended Audience :: Developers
Classifier: Operating System :: OS Independent
Classifier: Programming Language :: Python
Classifier: Programming Language :: Python :: 3
Classifier: Programming Language :: Python :: 3.10
Classifier: Programming Language :: Python :: 3.11
Classifier: Programming Language :: Python :: 3.12
Classifier: Topic :: Internet :: WWW/HTTP
Classifier: Topic :: Internet :: WWW/HTTP :: Dynamic Content
Requires-Python: >=3.10
License-File: LICENSE
Requires-Dist: Django>=4.0
Provides-Extra: dev
Requires-Dist: pytest>=7.0; extra == "dev"
Requires-Dist: pytest-django>=4.5; extra == "dev"
Requires-Dist: pytest-cov>=4.0; extra == "dev"
Requires-Dist: black>=23.0; extra == "dev"
Requires-Dist: flake8>=6.0; extra == "dev"
Requires-Dist: isort>=5.12; extra == "dev"
Requires-Dist: ruff>=0.1.0; extra == "dev"
Dynamic: license-file
